LICENSE
README.rst
setup.py
pysamoo/__init__.py
pysamoo/version.py
pysamoo.egg-info/PKG-INFO
pysamoo.egg-info/SOURCES.txt
pysamoo.egg-info/dependency_links.txt
pysamoo.egg-info/requires.txt
pysamoo.egg-info/top_level.txt
pysamoo/algorithms/__init__.py
pysamoo/algorithms/gpsaf.py
pysamoo/algorithms/psaf.py
pysamoo/algorithms/ssansga2.py
pysamoo/core/__init__.py
pysamoo/core/algorithm.py
pysamoo/core/archive.py
pysamoo/core/defaults.py
pysamoo/core/indicator.py
pysamoo/core/knockout.py
pysamoo/core/surrogate.py
pysamoo/core/target.py
pysamoo/core/tcv.py
pysamoo/experimental/SACOBRA.py
pysamoo/experimental/__init__.py
pysamoo/experimental/acquisition.py
pysamoo/experimental/bo.py
pysamoo/sampling/__init__.py
pysamoo/sampling/energy.py
pysamoo/sampling/niching.py
pysamoo/sampling/rejection.py
pysamoo/vendor/__init__.py
pysamoo/vendor/ego.py
pysamoo/vendor/lqcmaes.py
pysamoo/vendor/smac.py