Metadata-Version: 2.1
Name: pysamoo
Version: 0.1.2
Summary: Surrogate-Assisted Multi-objective Optimization
Home-page: https://anyoptimization.com/projects/pysamoo/
Author: Julian Blank
Author-email: blankjul@msu.edu
License: GNU AFFERO GENERAL PUBLIC LICENSE (AGPL)
Keywords: surrogate,metamodel,bayesian optimization
Platform: any
Classifier: Intended Audience :: Developers
Classifier: Intended Audience :: Science/Research
Classifier: Operating System :: OS Independent
Classifier: License :: OSI Approved :: Apache Software License
Classifier: Programming Language :: Python
Classifier: Programming Language :: Python :: 3
Classifier: Programming Language :: Python :: 3.7
Classifier: Programming Language :: Python :: 3.8
Classifier: Programming Language :: Python :: 3.9
Classifier: Programming Language :: Python :: 3.10
Classifier: Programming Language :: Python :: 3.11
Classifier: Topic :: Scientific/Engineering
Classifier: Topic :: Scientific/Engineering :: Artificial Intelligence
Classifier: Topic :: Scientific/Engineering :: Mathematics
Requires-Python: >=3.7
License-File: LICENSE
